mhnreact/__init__.py
mhnreact/data.py
mhnreact/inference.py
mhnreact/inspect.py
mhnreact/model.py
mhnreact/molutils.py
mhnreact/plotutils.py
mhnreact/retroeval.py
mhnreact/retrosyn.py
mhnreact/train.py
mhnreact/utils.py
mhnreact/view.py
syntheseus_mhnreact-1.0.dist-info/LICENSE
syntheseus_mhnreact-1.0.dist-info/METADATA
syntheseus_mhnreact-1.0.dist-info/WHEEL
syntheseus_mhnreact-1.0.dist-info/top_level.txt
syntheseus_mhnreact-1.0.dist-info/RECORD
