Metadata-Version: 2.1
Name: syntheseus-mhnreact
Version: 1.0
Summary: Fork of MHNreact for use in the syntheseus library
Home-page: https://github.com/kmaziarz/mhn-react
Classifier: Programming Language :: Python :: 3
Requires-Python: >=3.7
License-File: LICENSE
Requires-Dist: scikit-learn
Requires-Dist: scipy
Requires-Dist: swifter
Requires-Dist: tqdm
Requires-Dist: wandb
